[
  {
    "id": 533087958,
    "full_name": "terrastruct/d2",
    "stargazers_count": 5185,
    "open_issues_count": 94,
    "forks_count": 59
  },
  {
    "id": 565755421,
    "full_name": "openblocks-dev/openblocks",
    "stargazers_count": 3429,
    "open_issues_count": 34,
    "forks_count": 88
  },
  {
    "id": 54346799,
    "full_name": "public-apis/public-apis",
    "stargazers_count": 217756,
    "open_issues_count": 77,
    "forks_count": 24894
  },
  {
    "id": 132750724,
    "full_name": "codecrafters-io/build-your-own-x",
    "stargazers_count": 174724,
    "open_issues_count": 269,
    "forks_count": 16605
  },
  {
    "id": 215390876,
    "full_name": "malgamves/CommunityWriterPrograms",
    "stargazers_count": 2595,
    "open_issues_count": 3,
    "forks_count": 443
  },
  {
    "id": 184520105,
    "full_name": "sw-yx/spark-joy",
    "stargazers_count": 7759,
    "open_issues_count": 5,
    "forks_count": 290
  },
  {
    "id": 521655652,
    "full_name": "Infisical/infisical",
    "stargazers_count": 531,
    "open_issues_count": 18,
    "forks_count": 13
  },
  {
    "id": 529708137,
    "full_name": "steven-tey/dub",
    "stargazers_count": 3922,
    "open_issues_count": 25,
    "forks_count": 175
  },
  {
    "id": 523617129,
    "full_name": "csdojo-defaang/defaang",
    "stargazers_count": 487,
    "open_issues_count": 42,
    "forks_count": 118
  },
  {
    "id": 128193054,
    "full_name": "keystonejs/keystone",
    "stargazers_count": 7215,
    "open_issues_count": 117,
    "forks_count": 916
  },
  {
    "id": 105473537,
    "full_name": "BetterDiscord/BetterDiscord",
    "stargazers_count": 5704,
    "open_issues_count": 60,
    "forks_count": 886
  },
  {
    "id": 547362401,
    "full_name": "linvo-io/linvo-scraper",
    "stargazers_count": 490,
    "open_issues_count": 10,
    "forks_count": 44
  },
  {
    "id": 495836457,
    "full_name": "t3-oss/create-t3-app",
    "stargazers_count": 10679,
    "open_issues_count": 23,
    "forks_count": 435
  },
  {
    "id": 384219990,
    "full_name": "warpdotdev/Warp",
    "stargazers_count": 9551,
    "open_issues_count": 879,
    "forks_count": 142
  },
  {
    "id": 394318710,
    "full_name": "valinet/ExplorerPatcher",
    "stargazers_count": 9701,
    "open_issues_count": 0,
    "forks_count": 528
  },
  {
    "id": 8200767,
    "full_name": "toptal/gitignore.io",
    "stargazers_count": 7377,
    "open_issues_count": 11,
    "forks_count": 592
  },
  {
    "id": 125596489,
    "full_name": "doczjs/docz",
    "stargazers_count": 23012,
    "open_issues_count": 104,
    "forks_count": 1484
  },
  {
    "id": 468235985,
    "full_name": "taskless/taskless",
    "stargazers_count": 10,
    "open_issues_count": 2,
    "forks_count": 2
  },
  {
    "id": 60493101,
    "full_name": "jwasham/coding-interview-university",
    "stargazers_count": 239740,
    "open_issues_count": 50,
    "forks_count": 64061
  },
  {
    "id": 533647307,
    "full_name": "open-sauced/contributor.info",
    "stargazers_count": 4,
    "open_issues_count": 4,
    "forks_count": 1
  },
  {
    "id": 532466680,
    "full_name": "TechSquidTV/Shoutify",
    "stargazers_count": 186,
    "open_issues_count": 5,
    "forks_count": 23
  },
  {
    "id": 528144647,
    "full_name": "warmachine028/uemcrp",
    "stargazers_count": 25,
    "open_issues_count": 3,
    "forks_count": 37
  },
  {
    "id": 327089870,
    "full_name": "payloadcms/payload",
    "stargazers_count": 8489,
    "open_issues_count": 33,
    "forks_count": 372
  },
  {
    "id": 293860197,
    "full_name": "lowlighter/metrics",
    "stargazers_count": 8922,
    "open_issues_count": 12,
    "forks_count": 1034
  },
  {
    "id": 326281780,
    "full_name": "Gictorbit/illustratorCClinux",
    "stargazers_count": 608,
    "open_issues_count": 27,
    "forks_count": 85
  },
  {
    "id": 240308298,
    "full_name": "Gictorbit/photoshopCClinux",
    "stargazers_count": 3627,
    "open_issues_count": 79,
    "forks_count": 284
  },
  {
    "id": 71359796,
    "full_name": "open-sauced/open-sauced",
    "stargazers_count": 812,
    "open_issues_count": 10,
    "forks_count": 447
  },
  {
    "id": 525105056,
    "full_name": "karanpratapsingh/system-design",
    "stargazers_count": 13567,
    "open_issues_count": 2,
    "forks_count": 1031
  },
  {
    "id": 426820139,
    "full_name": "open-sauced/hot",
    "stargazers_count": 191,
    "open_issues_count": 33,
    "forks_count": 71
  },
  {
    "id": 506716260,
    "full_name": "TAKANOME-DEV/monorepo-template",
    "stargazers_count": 2,
    "open_issues_count": 5,
    "forks_count": 0
  }
]