[
  {
    "id": 77213120,
    "full_name": "Eugeny/tabby",
    "stargazers_count": 41092,
    "open_issues_count": 1155,
    "forks_count": 2522
  },
  {
    "id": 873328,
    "full_name": "getsentry/sentry",
    "stargazers_count": 32701,
    "open_issues_count": 685,
    "forks_count": 3666
  },
  {
    "id": 52630616,
    "full_name": "apollographql/apollo-client",
    "stargazers_count": 18270,
    "open_issues_count": 690,
    "forks_count": 2498
  },
  {
    "id": 45247496,
    "full_name": "snyk/cli",
    "stargazers_count": 4231,
    "open_issues_count": 178,
    "forks_count": 514
  },
  {
    "id": 20929025,
    "full_name": "microsoft/TypeScript",
    "stargazers_count": 86558,
    "open_issues_count": 5932,
    "forks_count": 11221
  },
  {
    "id": 464827989,
    "full_name": "apihero-run/jsonhero-web",
    "stargazers_count": 6746,
    "open_issues_count": 47,
    "forks_count": 281
  },
  {
    "id": 235901813,
    "full_name": "PostHog/posthog",
    "stargazers_count": 10061,
    "open_issues_count": 1378,
    "forks_count": 564
  },
  {
    "id": 527335176,
    "full_name": "t3-oss/create-t3-turbo",
    "stargazers_count": 1147,
    "open_issues_count": 10,
    "forks_count": 69
  },
  {
    "id": 80945428,
    "full_name": "nestjs/nest",
    "stargazers_count": 52551,
    "open_issues_count": 97,
    "forks_count": 6237
  },
  {
    "id": 453717720,
    "full_name": "AykutSarac/jsoncrack.com",
    "stargazers_count": 20044,
    "open_issues_count": 43,
    "forks_count": 982
  },
  {
    "id": 167032345,
    "full_name": "labs42io/clean-code-typescript",
    "stargazers_count": 6861,
    "open_issues_count": 7,
    "forks_count": 847
  },
  {
    "id": 121380371,
    "full_name": "thedevs-network/kutt",
    "stargazers_count": 6512,
    "open_issues_count": 145,
    "forks_count": 791
  },
  {
    "id": 372240402,
    "full_name": "alan2207/bulletproof-react",
    "stargazers_count": 15421,
    "open_issues_count": 32,
    "forks_count": 1310
  },
  {
    "id": 499330806,
    "full_name": "open-sauced/api.opensauced.pizza",
    "stargazers_count": 11,
    "open_issues_count": 20,
    "forks_count": 6
  },
  {
    "id": 162279822,
    "full_name": "agalwood/Motrix",
    "stargazers_count": 34595,
    "open_issues_count": 612,
    "forks_count": 3959
  },
  {
    "id": 26682105,
    "full_name": "darkreader/darkreader",
    "stargazers_count": 15487,
    "open_issues_count": 713,
    "forks_count": 2015
  },
  {
    "id": 102689445,
    "full_name": "mattermost/mattermost-webapp",
    "stargazers_count": 2164,
    "open_issues_count": 188,
    "forks_count": 2737
  },
  {
    "id": 245704608,
    "full_name": "colinhacks/zod",
    "stargazers_count": 14513,
    "open_issues_count": 136,
    "forks_count": 514
  },
  {
    "id": 214587193,
    "full_name": "supabase/supabase",
    "stargazers_count": 41757,
    "open_issues_count": 298,
    "forks_count": 2630
  },
  {
    "id": 400215964,
    "full_name": "novuhq/novu",
    "stargazers_count": 13773,
    "open_issues_count": 142,
    "forks_count": 857
  },
  {
    "id": 483406511,
    "full_name": "tremorlabs/tremor",
    "stargazers_count": 4975,
    "open_issues_count": 45,
    "forks_count": 95
  },
  {
    "id": 163883279,
    "full_name": "nektos/act",
    "stargazers_count": 32050,
    "open_issues_count": 83,
    "forks_count": 807
  },
  {
    "id": 533087958,
    "full_name": "terrastruct/d2",
    "stargazers_count": 7327,
    "open_issues_count": 104,
    "forks_count": 95
  },
  {
    "id": 565755421,
    "full_name": "openblocks-dev/openblocks",
    "stargazers_count": 3578,
    "open_issues_count": 41,
    "forks_count": 94
  },
  {
    "id": 54346799,
    "full_name": "public-apis/public-apis",
    "stargazers_count": 218690,
    "open_issues_count": 85,
    "forks_count": 25009
  },
  {
    "id": 132750724,
    "full_name": "codecrafters-io/build-your-own-x",
    "stargazers_count": 176670,
    "open_issues_count": 269,
    "forks_count": 16861
  },
  {
    "id": 215390876,
    "full_name": "malgamves/CommunityWriterPrograms",
    "stargazers_count": 2615,
    "open_issues_count": 5,
    "forks_count": 446
  },
  {
    "id": 184520105,
    "full_name": "sw-yx/spark-joy",
    "stargazers_count": 7787,
    "open_issues_count": 6,
    "forks_count": 290
  },
  {
    "id": 521655652,
    "full_name": "Infisical/infisical",
    "stargazers_count": 813,
    "open_issues_count": 40,
    "forks_count": 30
  },
  {
    "id": 529708137,
    "full_name": "steven-tey/dub",
    "stargazers_count": 4349,
    "open_issues_count": 27,
    "forks_count": 185
  }
]